[{"player_id":512,"player_name":"Jeong Woo-Yeong","firstname":"Woo-Yeong","lastname":"Jeong","number":null,"position":"Midfielder","age":21,"birth_date":"20/09/1999","birth_place":"Ulsan","birth_country":"Korea Republic","nationality":"Korea Republic","height":"180 cm","weight":"70 kg","injured":null,"rating":null,"team_id":160,"team_name":"SC Freiburg","league":"Bundesliga","season":"2019-2020","captain":0,"shots":{"total":0,"on":0},"goals":{"total":0,"conceded":0,"assists":0},"passes":{"total":0,"key":0,"accuracy":0},"tackles":{"total":0,"blocks":0,"interceptions":0},"duels":{"total":0,"won":0},"dribbles":{"attempts":0,"success":0},"fouls":{"drawn":0,"committed":0},"cards":{"yellow":0,"yellowred":0,"red":0},"penalty":{"won":0,"commited":0,"success":0,"missed":0,"saved":0},"games":{"appearences":0,"minutes_played":0,"lineups":0},"substitutes":{"in":0,"out":0,"bench":5}},{"player_id":512,"player_name":"Jeong Woo-Yeong","firstname":"Woo-Yeong","lastname":"Jeong","number":null,"position":"Midfielder","age":21,"birth_date":"20/09/1999","birth_place":"Ulsan","birth_country":"Korea Republic","nationality":"Korea Republic","height":"180 cm","weight":"70 kg","injured":null,"rating":"6.200000","team_id":160,"team_name":"SC Freiburg","league":"DFB Pokal","season":"2019-2020","captain":0,"shots":{"total":0,"on":0},"goals":{"total":0,"conceded":0,"assists":0},"passes":{"total":6,"key":0,"accuracy":54},"tackles":{"total":0,"blocks":0,"interceptions":0},"duels":{"total":0,"won":0},"dribbles":{"attempts":0,"success":0},"fouls":{"drawn":1,"committed":1},"cards":{"yellow":0,"yellowred":0,"red":0},"penalty":{"won":0,"commited":0,"success":0,"missed":0,"saved":0},"games":{"appearences":1,"minutes_played":33,"lineups":0},"substitutes":{"in":1,"out":0,"bench":2}},{"player_id":26234,"player_name":"A. Schwolow","firstname":"Alexander","lastname":"Schwolow","number":null,"position":"Goalkeeper","age":28,"birth_date":"02/06/1992","birth_place":"Wiesbaden","birth_country":"Germany","nationality":"Germany","height":"189 cm","weight":"84 kg","injured":null,"rating":"6.975000","team_id":160,"team_name":"SC Freiburg","league":"Bundesliga","season":"2019-2020","captain":0,"shots":{"total":0,"on":0},"goals":{"total":0,"conceded":21,"assists":0},"passes":{"total":361,"key":0,"accuracy":64},"tackles":{"total":0,"blocks":0,"interceptions":0},"duels":{"total":0,"won":0},"dribbles":{"attempts":0,"success":0},"fouls":{"drawn":1,"committed":0},"cards":{"yellow":0,"yellowred":0,"red":0},"penalty":{"won":0,"commited":0,"success":0,"missed":0,"saved":0},"games":{"appearences":16,"minutes_played":1373,"lineups":16},"substitutes":{"in":0,"out":1,"bench":0}},{"player_id":26234,"player_name":"A. Schwolow","firstname":"Alexander","lastname":"Schwolow","number":null,"position":"Goalkeeper","age":28,"birth_date":"02/06/1992","birth_place":"Wiesbaden","birth_country":"Germany","nationality":"Germany","height":"189 cm","weight":"84 kg","injured":null,"rating":"8.000000","team_id":160,"team_name":"SC Freiburg","league":"DFB Pokal","season":"2019-2020","captain":0,"shots":{"total":0,"on":0},"goals":{"total":0,"conceded":0,"assists":0},"passes":{"total":42,"key":0,"accuracy":77},"tackles":{"total":0,"blocks":0,"interceptions":0},"duels":{"total":0,"won":0},"dribbles":{"attempts":0,"success":0},"fouls":{"drawn":1,"committed":0},"cards":{"yellow":0,"yellowred":0,"red":0},"penalty":{"won":0,"commited":0,"success":0,"missed":0,"saved":0},"games":{"appearences":1,"minutes_played":120,"lineups":1},"substitutes":{"in":0,"out":0,"bench":0}},{"player_id":26232,"player_name":"M. Flekken","firstname":"Mark","lastname":"Flekken","number":null,"position":"Goalkeeper","age":27,"birth_date":"13/06/1993","birth_place":null,"birth_country":"Netherlands","nationality":"Netherlands","height":"193 cm","weight":"85 kg","injured":null,"rating":"7.322222","team_id":160,"team_name":"SC Freiburg","league":"Bundesliga","season":"2019-2020","captain":0,"shots":{"total":0,"on":0},"goals":{"total":0,"conceded":14,"assists":0},"passes":{"total":226,"key":0,"accuracy":65},"tackles":{"total":0,"blocks":0,"interceptions":1},"duels":{"total":0,"won":0},"dribbles":{"attempts":0,"success":0},"fouls":{"drawn":0,"committed":1},"cards":{"yellow":0,"yellowred":0,"red":0},"penalty":{"won":0,"commited":0,"success":0,"missed":0,"saved":0},"games":{"appearences":9,"minutes_played":810,"lineups":9},"substitutes":{"in":0,"out":0,"bench":9}},{"player_id":26232,"player_name":"M. Flekken","firstname":"Mark","lastname":"Flekken","number":null,"position":"Goalkeeper","age":27,"birth_date":"13/06/1993","birth_place":null,"birth_country":"Netherlands","nationality":"Netherlands","height":"193 cm","weight":"85 kg","injured":null,"rating":"6.300000","team_id":160,"team_name":"SC Freiburg","league":"DFB Pokal","season":"2019-2020","captain":0,"shots":{"total":0,"on":0},"goals":{"total":0,"conceded":3,"assists":0},"passes":{"total":38,"key":0,"accuracy":63},"tackles":{"total":0,"blocks":0,"interceptions":0},"duels":{"total":0,"won":0},"dribbles":{"attempts":0,"success":0},"fouls":{"drawn":0,"committed":0},"cards":{"yellow":0,"yellowred":0,"red":0},"penalty":{"won":0,"commited":0,"success":0,"missed":0,"saved":0},"games":{"appearences":1,"minutes_played":90,"lineups":1},"substitutes":{"in":0,"out":0,"bench":0}},{"player_id":127929,"player_name":"N. Thiede","firstname":"Niclas","lastname":"Thiede","number":null,"position":"Goalkeeper","age":21,"birth_date":"14/04/1999","birth_place":"Hagen","birth_country":"Germany","nationality":"Germany","height":"187 cm","weight":null,"injured":null,"rating":"6.800000","team_id":160,"team_name":"SC Freiburg","league":"Bundesliga","season":"2019-2020","captain":0,"shots":{"total":0,"on":0},"goals":{"total":0,"conceded":2,"assists":0},"passes":{"total":21,"key":0,"accuracy":70},"tackles":{"total":0,"blocks":0,"interceptions":0},"duels":{"total":0,"won":0},"dribbles":{"attempts":0,"success":0},"fouls":{"drawn":1,"committed":0},"cards":{"yellow":0,"yellowred":0,"red":0},"penalty":{"won":0,"commited":0,"success":0,"missed":0,"saved":0},"games":{"appearences":1,"minutes_played":67,"lineups":0},"substitutes":{"in":1,"out":0,"bench":16}},{"player_id":127929,"player_name":"N. Thiede","firstname":"Niclas","lastname":"Thiede","number":null,"position":"Goalkeeper","age":21,"birth_date":"14/04/1999","birth_place":"Hagen","birth_country":"Germany","nationality":"Germany","height":"187 cm","weight":null,"injured":null,"rating":null,"team_id":160,"team_name":"SC Freiburg","league":"DFB Pokal","season":"2019-2020","captain":0,"shots":{"total":0,"on":0},"goals":{"total":0,"conceded":0,"assists":0},"passes":{"total":0,"key":0,"accuracy":0},"tackles":{"total":0,"blocks":0,"interceptions":0},"duels":{"total":0,"won":0},"dribbles":{"attempts":0,"success":0},"fouls":{"drawn":0,"committed":0},"cards":{"yellow":0,"yellowred":0,"red":0},"penalty":{"won":0,"commited":0,"success":0,"missed":0,"saved":0},"games":{"appearences":0,"minutes_played":0,"lineups":0},"substitutes":{"in":0,"out":0,"bench":2}},{"player_id":26240,"player_name":"P. Lienhart","firstname":"Philipp","lastname":"Lienhart","number":null,"position":"Defender","age":24,"birth_date":"11/07/1996","birth_place":"Lilienfeld","birth_country":"Austria","nationality":"Austria","height":"189 cm","weight":"80 kg","injured":null,"rating":"6.953846","team_id":160,"team_name":"SC Freiburg","league":"Bundesliga","season":"2019-2020","captain":0,"shots":{"total":4,"on":2},"goals":{"total":0,"conceded":0,"assists":1},"passes":{"total":624,"key":2,"accuracy":81},"tackles":{"total":7,"blocks":9,"interceptions":19},"duels":{"total":0,"won":0},"dribbles":{"attempts":2,"success":2},"fouls":{"drawn":18,"committed":6},"cards":{"yellow":2,"yellowred":0,"red":0},"penalty":{"won":0,"commited":0,"success":0,"missed":0,"saved":0},"games":{"appearences":14,"minutes_played":1170,"lineups":13},"substitutes":{"in":1,"out":0,"bench":7}},{"player_id":26240,"player_name":"P. Lienhart","firstname":"Philipp","lastname":"Lienhart","number":null,"position":"Defender","age":24,"birth_date":"11/07/1996","birth_place":"Lilienfeld","birth_country":"Austria","nationality":"Austria","height":"189 cm","weight":"80 kg","injured":null,"rating":"6.950000","team_id":160,"team_name":"SC Freiburg","league":"DFB Pokal","season":"2019-2020","captain":0,"shots":{"total":0,"on":0},"goals":{"total":0,"conceded":0,"assists":0},"passes":{"total":113,"key":0,"accuracy":85},"tackles":{"total":1,"blocks":0,"interceptions":3},"duels":{"total":0,"won":0},"dribbles":{"attempts":1,"success":1},"fouls":{"drawn":1,"committed":2},"cards":{"yellow":0,"yellowred":0,"red":0},"penalty":{"won":0,"commited":0,"success":0,"missed":0,"saved":0},"games":{"appearences":2,"minutes_played":131,"lineups":1},"substitutes":{"in":1,"out":0,"bench":1}},{"player_id":26243,"player_name":"N. Schlotterbeck","firstname":"Nico","lastname":"Schlotterbeck","number":null,"position":"Defender","age":21,"birth_date":"01/12/1999","birth_place":null,"birth_country":"Germany","nationality":"Germany","height":"191 cm","weight":null,"injured":null,"rating":"6.842857","team_id":160,"team_name":"SC Freiburg","league":"Bundesliga","season":"2019-2020","captain":0,"shots":{"total":3,"on":1},"goals":{"total":0,"conceded":0,"assists":0},"passes":{"total":153,"key":3,"accuracy":66},"tackles":{"total":3,"blocks":5,"interceptions":4},"duels":{"total":0,"won":0},"dribbles":{"attempts":3,"success":3},"fouls":{"drawn":9,"committed":6},"cards":{"yellow":0,"yellowred":0,"red":0},"penalty":{"won":0,"commited":0,"success":0,"missed":0,"saved":0},"games":{"appearences":11,"minutes_played":365,"lineups":4},"substitutes":{"in":7,"out":1,"bench":20}},{"player_id":26243,"player_name":"N. Schlotterbeck","firstname":"Nico","lastname":"Schlotterbeck","number":null,"position":"Defender","age":21,"birth_date":"01/12/1999","birth_place":null,"birth_country":"Germany","nationality":"Germany","height":"191 cm","weight":null,"injured":null,"rating":"5.800000","team_id":160,"team_name":"SC Freiburg","league":"DFB Pokal","season":"2019-2020","captain":0,"shots":{"total":1,"on":0},"goals":{"total":0,"conceded":0,"assists":0},"passes":{"total":57,"key":0,"accuracy":91},"tackles":{"total":1,"blocks":0,"interceptions":0},"duels":{"total":0,"won":0},"dribbles":{"attempts":0,"success":0},"fouls":{"drawn":3,"committed":1},"cards":{"yellow":1,"yellowred":0,"red":0},"penalty":{"won":0,"commited":0,"success":0,"missed":0,"saved":0},"games":{"appearences":1,"minutes_played":90,"lineups":1},"substitutes":{"in":0,"out":0,"bench":1}},{"player_id":26235,"player_name":"M. Gulde","firstname":"Manuel","lastname":"Gulde","number":null,"position":"Defender","age":29,"birth_date":"12/02/1991","birth_place":"Mannheim","birth_country":"Germany","nationality":"Germany","height":"184 cm","weight":"78 kg","injured":null,"rating":"7.023076","team_id":160,"team_name":"SC Freiburg","league":"Bundesliga","season":"2019-2020","captain":0,"shots":{"total":12,"on":2},"goals":{"total":0,"conceded":0,"assists":0},"passes":{"total":537,"key":4,"accuracy":83},"tackles":{"total":23,"blocks":10,"interceptions":19},"duels":{"total":0,"won":0},"dribbles":{"attempts":5,"success":5},"fouls":{"drawn":8,"committed":6},"cards":{"yellow":0,"yellowred":0,"red":0},"penalty":{"won":0,"commited":0,"success":0,"missed":0,"saved":0},"games":{"appearences":13,"minutes_played":1079,"lineups":12},"substitutes":{"in":1,"out":4,"bench":7}},{"player_id":26235,"player_name":"M. Gulde","firstname":"Manuel","lastname":"Gulde","number":null,"position":"Defender","age":29,"birth_date":"12/02/1991","birth_place":"Mannheim","birth_country":"Germany","nationality":"Germany","height":"184 cm","weight":"78 kg","injured":null,"rating":null,"team_id":160,"team_name":"SC Freiburg","league":"DFB Pokal","season":"2019-2020","captain":0,"shots":{"total":0,"on":0},"goals":{"total":0,"conceded":0,"assists":0},"passes":{"total":0,"key":0,"accuracy":0},"tackles":{"total":0,"blocks":0,"interceptions":0},"duels":{"total":0,"won":0},"dribbles":{"attempts":0,"success":0},"fouls":{"drawn":0,"committed":0},"cards":{"yellow":0,"yellowred":0,"red":0},"penalty":{"won":0,"commited":0,"success":0,"missed":0,"saved":0},"games":{"appearences":0,"minutes_played":0,"lineups":0},"substitutes":{"in":0,"out":0,"bench":1}},{"player_id":26239,"player_name":"L. Kübler","firstname":"Lukas","lastname":"Kübler","number":null,"position":"Defender","age":28,"birth_date":"30/08/1992","birth_place":"Bonn","birth_country":"Germany","nationality":"Germany","height":"182 cm","weight":"73 kg","injured":null,"rating":"6.300000","team_id":160,"team_name":"SC Freiburg","league":"Bundesliga","season":"2019-2020","captain":0,"shots":{"total":1,"on":0},"goals":{"total":0,"conceded":0,"assists":0},"passes":{"total":40,"key":0,"accuracy":27},"tackles":{"total":0,"blocks":0,"interceptions":0},"duels":{"total":0,"won":0},"dribbles":{"attempts":2,"success":2},"fouls":{"drawn":0,"committed":1},"cards":{"yellow":0,"yellowred":0,"red":0},"penalty":{"won":0,"commited":0,"success":0,"missed":0,"saved":0},"games":{"appearences":3,"minutes_played":87,"lineups":1},"substitutes":{"in":2,"out":1,"bench":3}},{"player_id":26239,"player_name":"L. Kübler","firstname":"Lukas","lastname":"Kübler","number":null,"position":"Defender","age":28,"birth_date":"30/08/1992","birth_place":"Bonn","birth_country":"Germany","nationality":"Germany","height":"182 cm","weight":"73 kg","injured":null,"rating":null,"team_id":160,"team_name":"SC Freiburg","league":"DFB Pokal","season":"2019-2020","captain":0,"shots":{"total":0,"on":0},"goals":{"total":0,"conceded":0,"assists":0},"passes":{"total":0,"key":0,"accuracy":0},"tackles":{"total":0,"blocks":0,"interceptions":0},"duels":{"total":0,"won":0},"dribbles":{"attempts":0,"success":0},"fouls":{"drawn":0,"committed":0},"cards":{"yellow":0,"yellowred":0,"red":0},"penalty":{"won":0,"commited":0,"success":0,"missed":0,"saved":0},"games":{"appearences":0,"minutes_played":0,"lineups":0},"substitutes":{"in":0,"out":0,"bench":0}},{"player_id":26237,"player_name":"D. Heintz","firstname":"Dominique","lastname":"Heintz","number":null,"position":"Defender","age":27,"birth_date":"15/08/1993","birth_place":"Neustadt an der Weinstraße","birth_country":"Germany","nationality":"Germany","height":"188 cm","weight":"89 kg","injured":null,"rating":"6.961904","team_id":160,"team_name":"SC Freiburg","league":"Bundesliga","season":"2019-2020","captain":0,"shots":{"total":4,"on":2},"goals":{"total":0,"conceded":0,"assists":1},"passes":{"total":820,"key":4,"accuracy":79},"tackles":{"total":39,"blocks":21,"interceptions":33},"duels":{"total":0,"won":0},"dribbles":{"attempts":17,"success":15},"fouls":{"drawn":13,"committed":12},"cards":{"yellow":2,"yellowred":0,"red":0},"penalty":{"won":0,"commited":1,"success":0,"missed":0,"saved":0},"games":{"appearences":21,"minutes_played":1804,"lineups":20},"substitutes":{"in":1,"out":1,"bench":5}},{"player_id":26237,"player_name":"D. Heintz","firstname":"Dominique","lastname":"Heintz","number":null,"position":"Defender","age":27,"birth_date":"15/08/1993","birth_place":"Neustadt an der Weinstraße","birth_country":"Germany","nationality":"Germany","height":"188 cm","weight":"89 kg","injured":null,"rating":"7.500000","team_id":160,"team_name":"SC Freiburg","league":"DFB Pokal","season":"2019-2020","captain":0,"shots":{"total":1,"on":0},"goals":{"total":0,"conceded":0,"assists":0},"passes":{"total":139,"key":2,"accuracy":83},"tackles":{"total":4,"blocks":2,"interceptions":2},"duels":{"total":0,"won":0},"dribbles":{"attempts":2,"success":2},"fouls":{"drawn":2,"committed":1},"cards":{"yellow":1,"yellowred":0,"red":0},"penalty":{"won":0,"commited":0,"success":0,"missed":0,"saved":0},"games":{"appearences":2,"minutes_played":210,"lineups":2},"substitutes":{"in":0,"out":0,"bench":0}},{"player_id":25401,"player_name":"G. Itter","firstname":"Gian-Luca","lastname":"Itter","number":null,"position":"Defender","age":21,"birth_date":"05/01/1999","birth_place":"Gießen","birth_country":"Germany","nationality":"Germany","height":"184 cm","weight":"72 kg","injured":null,"rating":"6.700000","team_id":160,"team_name":"SC Freiburg","league":"Bundesliga","season":"2019-2020","captain":0,"shots":{"total":0,"on":0},"goals":{"total":0,"conceded":0,"assists":0},"passes":{"total":2,"key":0,"accuracy":100},"tackles":{"total":0,"blocks":0,"interceptions":0},"duels":{"total":0,"won":0},"dribbles":{"attempts":0,"success":0},"fouls":{"drawn":0,"committed":0},"cards":{"yellow":0,"yellowred":0,"red":0},"penalty":{"won":0,"commited":0,"success":0,"missed":0,"saved":0},"games":{"appearences":1,"minutes_played":4,"lineups":0},"substitutes":{"in":1,"out":0,"bench":12}},{"player_id":26238,"player_name":"R. Koch","firstname":"Robin","lastname":"Koch","number":null,"position":"Defender","age":24,"birth_date":"17/07/1996","birth_place":"Kaiserslautern","birth_country":"Germany","nationality":"Germany","height":"192 cm","weight":"85 kg","injured":null,"rating":"6.995833","team_id":160,"team_name":"SC Freiburg","league":"Bundesliga","season":"2019-2020","captain":0,"shots":{"total":24,"on":7},"goals":{"total":1,"conceded":0,"assists":0},"passes":{"total":1029,"key":11,"accuracy":82},"tackles":{"total":23,"blocks":16,"interceptions":32},"duels":{"total":0,"won":0},"dribbles":{"attempts":4,"success":4},"fouls":{"drawn":18,"committed":22},"cards":{"yellow":2,"yellowred":0,"red":0},"penalty":{"won":0,"commited":0,"success":0,"missed":0,"saved":0},"games":{"appearences":24,"minutes_played":2098,"lineups":24},"substitutes":{"in":0,"out":1,"bench":0}},{"player_id":26238,"player_name":"R. Koch","firstname":"Robin","lastname":"Koch","number":null,"position":"Defender","age":24,"birth_date":"17/07/1996","birth_place":"Kaiserslautern","birth_country":"Germany","nationality":"Germany","height":"192 cm","weight":"85 kg","injured":null,"rating":"6.950000","team_id":160,"team_name":"SC Freiburg","league":"DFB Pokal","season":"2019-2020","captain":0,"shots":{"total":1,"on":1},"goals":{"total":1,"conceded":0,"assists":0},"passes":{"total":52,"key":0,"accuracy":91},"tackles":{"total":2,"blocks":0,"interceptions":1},"duels":{"total":0,"won":0},"dribbles":{"attempts":0,"success":0},"fouls":{"drawn":1,"committed":2},"cards":{"yellow":1,"yellowred":0,"red":0},"penalty":{"won":0,"commited":0,"success":0,"missed":0,"saved":0},"games":{"appearences":2,"minutes_played":99,"lineups":1},"substitutes":{"in":1,"out":0,"bench":1}},{"player_id":26236,"player_name":"C. Günter","firstname":"Christian","lastname":"Günter","number":null,"position":"Defender","age":27,"birth_date":"28/02/1993","birth_place":"Villingen-Schwenningen","birth_country":"Germany","nationality":"Germany","height":"184 cm","weight":"83 kg","injured":null,"rating":"7.000000","team_id":160,"team_name":"SC Freiburg","league":"Bundesliga","season":"2019-2020","captain":22,"shots":{"total":29,"on":8},"goals":{"total":2,"conceded":0,"assists":5},"passes":{"total":530,"key":54,"accuracy":71},"tackles":{"total":18,"blocks":11,"interceptions":11},"duels":{"total":0,"won":0},"dribbles":{"attempts":36,"success":14},"fouls":{"drawn":17,"committed":14},"cards":{"yellow":2,"yellowred":0,"red":0},"penalty":{"won":1,"commited":0,"success":0,"missed":0,"saved":0},"games":{"appearences":25,"minutes_played":2238,"lineups":25},"substitutes":{"in":0,"out":1,"bench":0}},{"player_id":26236,"player_name":"C. Günter","firstname":"Christian","lastname":"Günter","number":null,"position":"Defender","age":27,"birth_date":"28/02/1993","birth_place":"Villingen-Schwenningen","birth_country":"Germany","nationality":"Germany","height":"184 cm","weight":"83 kg","injured":null,"rating":"6.650000","team_id":160,"team_name":"SC Freiburg","league":"DFB Pokal","season":"2019-2020","captain":0,"shots":{"total":1,"on":0},"goals":{"total":0,"conceded":0,"assists":0},"passes":{"total":68,"key":3,"accuracy":80},"tackles":{"total":0,"blocks":1,"interceptions":0},"duels":{"total":0,"won":0},"dribbles":{"attempts":5,"success":2},"fouls":{"drawn":1,"committed":2},"cards":{"yellow":0,"yellowred":0,"red":0},"penalty":{"won":0,"commited":0,"success":0,"missed":0,"saved":0},"games":{"appearences":2,"minutes_played":210,"lineups":2},"substitutes":{"in":0,"out":0,"bench":0}},{"player_id":26245,"player_name":"A. Abrashi","firstname":"Amir","lastname":"Abrashi","number":null,"position":"Midfielder","age":30,"birth_date":"27/03/1990","birth_place":"Bischofszell","birth_country":"Switzerland","nationality":"Albania","height":"172 cm","weight":"71 kg","injured":null,"rating":"6.625000","team_id":160,"team_name":"SC Freiburg","league":"Bundesliga","season":"2019-2020","captain":0,"shots":{"total":4,"on":2},"goals":{"total":0,"conceded":0,"assists":0},"passes":{"total":206,"key":3,"accuracy":87},"tackles":{"total":12,"blocks":2,"interceptions":6},"duels":{"total":0,"won":0},"dribbles":{"attempts":4,"success":2},"fouls":{"drawn":6,"committed":13},"cards":{"yellow":3,"yellowred":0,"red":0},"penalty":{"won":0,"commited":0,"success":0,"missed":0,"saved":0},"games":{"appearences":9,"minutes_played":532,"lineups":7},"substitutes":{"in":2,"out":4,"bench":11}},{"player_id":26245,"player_name":"A. Abrashi","firstname":"Amir","lastname":"Abrashi","number":null,"position":"Midfielder","age":30,"birth_date":"27/03/1990","birth_place":"Bischofszell","birth_country":"Switzerland","nationality":"Albania","height":"172 cm","weight":"71 kg","injured":null,"rating":null,"team_id":160,"team_name":"SC Freiburg","league":"DFB Pokal","season":"2019-2020","captain":0,"shots":{"total":0,"on":0},"goals":{"total":0,"conceded":0,"assists":0},"passes":{"total":0,"key":0,"accuracy":0},"tackles":{"total":0,"blocks":0,"interceptions":0},"duels":{"total":0,"won":0},"dribbles":{"attempts":0,"success":0},"fouls":{"drawn":0,"committed":0},"cards":{"yellow":0,"yellowred":0,"red":0},"penalty":{"won":0,"commited":0,"success":0,"missed":0,"saved":0},"games":{"appearences":0,"minutes_played":0,"lineups":0},"substitutes":{"in":0,"out":0,"bench":1}},{"player_id":25303,"player_name":"J. Schmid","firstname":"Jonathan","lastname":"Schmid","number":null,"position":"Midfielder","age":30,"birth_date":"22/06/1990","birth_place":"Strasbourg","birth_country":"France","nationality":"France","height":"179 cm","weight":"79 kg","injured":null,"rating":"6.875000","team_id":160,"team_name":"SC Freiburg","league":"Bundesliga","season":"2019-2020","captain":0,"shots":{"total":35,"on":13},"goals":{"total":4,"conceded":0,"assists":1},"passes":{"total":614,"key":21,"accuracy":69},"tackles":{"total":23,"blocks":3,"interceptions":23},"duels":{"total":0,"won":0},"dribbles":{"attempts":23,"success":11},"fouls":{"drawn":27,"committed":12},"cards":{"yellow":1,"yellowred":0,"red":0},"penalty":{"won":0,"commited":0,"success":0,"missed":0,"saved":0},"games":{"appearences":24,"minutes_played":2153,"lineups":24},"substitutes":{"in":0,"out":4,"bench":0}},{"player_id":25303,"player_name":"J. Schmid","firstname":"Jonathan","lastname":"Schmid","number":null,"position":"Midfielder","age":30,"birth_date":"22/06/1990","birth_place":"Strasbourg","birth_country":"France","nationality":"France","height":"179 cm","weight":"79 kg","injured":null,"rating":"6.950000","team_id":160,"team_name":"SC Freiburg","league":"DFB Pokal","season":"2019-2020","captain":0,"shots":{"total":0,"on":0},"goals":{"total":0,"conceded":0,"assists":0},"passes":{"total":70,"key":1,"accuracy":79},"tackles":{"total":2,"blocks":0,"interceptions":1},"duels":{"total":0,"won":0},"dribbles":{"attempts":3,"success":2},"fouls":{"drawn":8,"committed":1},"cards":{"yellow":0,"yellowred":0,"red":0},"penalty":{"won":0,"commited":0,"success":0,"missed":0,"saved":0},"games":{"appearences":2,"minutes_played":210,"lineups":2},"substitutes":{"in":0,"out":0,"bench":0}},{"player_id":26246,"player_name":"M. Frantz","firstname":"Mike","lastname":"Frantz","number":null,"position":"Midfielder","age":34,"birth_date":"14/10/1986","birth_place":"Saarbrücken","birth_country":"Germany","nationality":"Germany","height":"182 cm","weight":"81 kg","injured":null,"rating":"6.700000","team_id":160,"team_name":"SC Freiburg","league":"Bundesliga","season":"2019-2020","captain":3,"shots":{"total":4,"on":1},"goals":{"total":0,"conceded":0,"assists":1},"passes":{"total":53,"key":6,"accuracy":44},"tackles":{"total":3,"blocks":2,"interceptions":0},"duels":{"total":0,"won":0},"dribbles":{"attempts":1,"success":1},"fouls":{"drawn":5,"committed":6},"cards":{"yellow":2,"yellowred":0,"red":0},"penalty":{"won":0,"commited":0,"success":0,"missed":0,"saved":0},"games":{"appearences":11,"minutes_played":257,"lineups":3},"substitutes":{"in":8,"out":3,"bench":15}},{"player_id":26246,"player_name":"M. Frantz","firstname":"Mike","lastname":"Frantz","number":null,"position":"Midfielder","age":34,"birth_date":"14/10/1986","birth_place":"Saarbrücken","birth_country":"Germany","nationality":"Germany","height":"182 cm","weight":"81 kg","injured":null,"rating":"6.550000","team_id":160,"team_name":"SC Freiburg","league":"DFB Pokal","season":"2019-2020","captain":2,"shots":{"total":1,"on":0},"goals":{"total":0,"conceded":0,"assists":0},"passes":{"total":59,"key":3,"accuracy":85},"tackles":{"total":1,"blocks":0,"interceptions":0},"duels":{"total":0,"won":0},"dribbles":{"attempts":0,"success":0},"fouls":{"drawn":0,"committed":4},"cards":{"yellow":0,"yellowred":0,"red":0},"penalty":{"won":0,"commited":0,"success":0,"missed":0,"saved":0},"games":{"appearences":2,"minutes_played":157,"lineups":2},"substitutes":{"in":0,"out":2,"bench":0}},{"player_id":48586,"player_name":"Y. Ravet","firstname":"Yoric","lastname":"Ravet","number":null,"position":"Midfielder","age":31,"birth_date":"12/09/1989","birth_place":"Échirolles","birth_country":"France","nationality":"France","height":"178 cm","weight":"78 kg","injured":null,"rating":null,"team_id":160,"team_name":"SC Freiburg","league":"Bundesliga","season":"2019-2020","captain":0,"shots":{"total":0,"on":0},"goals":{"total":0,"conceded":0,"assists":0},"passes":{"total":0,"key":0,"accuracy":0},"tackles":{"total":0,"blocks":0,"interceptions":0},"duels":{"total":0,"won":0},"dribbles":{"attempts":0,"success":0},"fouls":{"drawn":0,"committed":0},"cards":{"yellow":0,"yellowred":0,"red":0},"penalty":{"won":0,"commited":0,"success":0,"missed":0,"saved":0},"games":{"appearences":0,"minutes_played":0,"lineups":0},"substitutes":{"in":0,"out":0,"bench":3}},{"player_id":26249,"player_name":"J. Haberer","firstname":"Janik","lastname":"Haberer","number":null,"position":"Midfielder","age":26,"birth_date":"02/04/1994","birth_place":"Wangen im Allgäu","birth_country":"Germany","nationality":"Germany","height":"186 cm","weight":"77 kg","injured":null,"rating":"6.790476","team_id":160,"team_name":"SC Freiburg","league":"Bundesliga","season":"2019-2020","captain":0,"shots":{"total":12,"on":3},"goals":{"total":2,"conceded":0,"assists":2},"passes":{"total":681,"key":16,"accuracy":81},"tackles":{"total":24,"blocks":4,"interceptions":23},"duels":{"total":0,"won":0},"dribbles":{"attempts":26,"success":16},"fouls":{"drawn":36,"committed":29},"cards":{"yellow":4,"yellowred":1,"red":0},"penalty":{"won":0,"commited":0,"success":0,"missed":0,"saved":0},"games":{"appearences":21,"minutes_played":1615,"lineups":19},"substitutes":{"in":2,"out":6,"bench":2}},{"player_id":26249,"player_name":"J. Haberer","firstname":"Janik","lastname":"Haberer","number":null,"position":"Midfielder","age":26,"birth_date":"02/04/1994","birth_place":"Wangen im Allgäu","birth_country":"Germany","nationality":"Germany","height":"186 cm","weight":"77 kg","injured":null,"rating":"6.300000","team_id":160,"team_name":"SC Freiburg","league":"DFB Pokal","season":"2019-2020","captain":0,"shots":{"total":1,"on":0},"goals":{"total":0,"conceded":0,"assists":0},"passes":{"total":45,"key":1,"accuracy":81},"tackles":{"total":0,"blocks":2,"interceptions":1},"duels":{"total":0,"won":0},"dribbles":{"attempts":2,"success":2},"fouls":{"drawn":2,"committed":2},"cards":{"yellow":0,"yellowred":0,"red":0},"penalty":{"won":0,"commited":0,"success":0,"missed":0,"saved":0},"games":{"appearences":1,"minutes_played":90,"lineups":1},"substitutes":{"in":0,"out":0,"bench":0}},{"player_id":26250,"player_name":"N. Höfler","firstname":"Nicolas","lastname":"Höfler","number":null,"position":"Midfielder","age":30,"birth_date":"09/03/1990","birth_place":"Überlingen","birth_country":"Germany","nationality":"Germany","height":"181 cm","weight":"78 kg","injured":null,"rating":"6.965217","team_id":160,"team_name":"SC Freiburg","league":"Bundesliga","season":"2019-2020","captain":0,"shots":{"total":21,"on":2},"goals":{"total":1,"conceded":0,"assists":0},"passes":{"total":913,"key":12,"accuracy":84},"tackles":{"total":47,"blocks":14,"interceptions":47},"duels":{"total":0,"won":0},"dribbles":{"attempts":34,"success":25},"fouls":{"drawn":22,"committed":36},"cards":{"yellow":7,"yellowred":0,"red":0},"penalty":{"won":1,"commited":0,"success":0,"missed":0,"saved":0},"games":{"appearences":23,"minutes_played":1991,"lineups":22},"substitutes":{"in":1,"out":2,"bench":1}},{"player_id":26250,"player_name":"N. Höfler","firstname":"Nicolas","lastname":"Höfler","number":null,"position":"Midfielder","age":30,"birth_date":"09/03/1990","birth_place":"Überlingen","birth_country":"Germany","nationality":"Germany","height":"181 cm","weight":"78 kg","injured":null,"rating":"6.900000","team_id":160,"team_name":"SC Freiburg","league":"DFB Pokal","season":"2019-2020","captain":0,"shots":{"total":2,"on":0},"goals":{"total":0,"conceded":0,"assists":0},"passes":{"total":67,"key":1,"accuracy":90},"tackles":{"total":2,"blocks":0,"interceptions":3},"duels":{"total":0,"won":0},"dribbles":{"attempts":2,"success":2},"fouls":{"drawn":2,"committed":3},"cards":{"yellow":0,"yellowred":0,"red":0},"penalty":{"won":0,"commited":0,"success":0,"missed":0,"saved":0},"games":{"appearences":1,"minutes_played":120,"lineups":1},"substitutes":{"in":0,"out":0,"bench":0}},{"player_id":26248,"player_name":"V. Grifo","firstname":"Vincenzo","lastname":"Grifo","number":null,"position":"Midfielder","age":27,"birth_date":"07/04/1993","birth_place":"Pforzheim","birth_country":"Germany","nationality":"Italy","height":"180 cm","weight":"72 kg","injured":null,"rating":"6.894117","team_id":160,"team_name":"SC Freiburg","league":"Bundesliga","season":"2019-2020","captain":0,"shots":{"total":31,"on":13},"goals":{"total":2,"conceded":0,"assists":3},"passes":{"total":283,"key":24,"accuracy":74},"tackles":{"total":9,"blocks":0,"interceptions":7},"duels":{"total":0,"won":0},"dribbles":{"attempts":34,"success":18},"fouls":{"drawn":9,"committed":5},"cards":{"yellow":1,"yellowred":0,"red":1},"penalty":{"won":0,"commited":0,"success":1,"missed":0,"saved":0},"games":{"appearences":17,"minutes_played":962,"lineups":8},"substitutes":{"in":9,"out":6,"bench":9}},{"player_id":26248,"player_name":"V. Grifo","firstname":"Vincenzo","lastname":"Grifo","number":null,"position":"Midfielder","age":27,"birth_date":"07/04/1993","birth_place":"Pforzheim","birth_country":"Germany","nationality":"Italy","height":"180 cm","weight":"72 kg","injured":null,"rating":"7.500000","team_id":160,"team_name":"SC Freiburg","league":"DFB Pokal","season":"2019-2020","captain":0,"shots":{"total":1,"on":0},"goals":{"total":0,"conceded":0,"assists":1},"passes":{"total":24,"key":3,"accuracy":63},"tackles":{"total":2,"blocks":0,"interceptions":1},"duels":{"total":0,"won":0},"dribbles":{"attempts":3,"success":1},"fouls":{"drawn":0,"committed":1},"cards":{"yellow":0,"yellowred":0,"red":0},"penalty":{"won":0,"commited":0,"success":0,"missed":0,"saved":0},"games":{"appearences":1,"minutes_played":90,"lineups":1},"substitutes":{"in":0,"out":0,"bench":0}},{"player_id":127928,"player_name":"L. Tempelmann","firstname":"Lino","lastname":"Tempelmann","number":null,"position":"Midfielder","age":21,"birth_date":"02/02/1999","birth_place":null,"birth_country":"Germany","nationality":"Germany","height":"175 cm","weight":"72 kg","injured":null,"rating":"6.700000","team_id":160,"team_name":"SC Freiburg","league":"Bundesliga","season":"2019-2020","captain":0,"shots":{"total":1,"on":0},"goals":{"total":0,"conceded":0,"assists":0},"passes":{"total":6,"key":0,"accuracy":60},"tackles":{"total":1,"blocks":1,"interceptions":0},"duels":{"total":0,"won":0},"dribbles":{"attempts":1,"success":1},"fouls":{"drawn":0,"committed":1},"cards":{"yellow":0,"yellowred":0,"red":0},"penalty":{"won":0,"commited":0,"success":0,"missed":0,"saved":0},"games":{"appearences":1,"minutes_played":34,"lineups":1},"substitutes":{"in":0,"out":1,"bench":10}},{"player_id":127928,"player_name":"L. Tempelmann","firstname":"Lino","lastname":"Tempelmann","number":null,"position":"Midfielder","age":21,"birth_date":"02/02/1999","birth_place":null,"birth_country":"Germany","nationality":"Germany","height":"175 cm","weight":"72 kg","injured":null,"rating":null,"team_id":160,"team_name":"SC Freiburg","league":"DFB Pokal","season":"2019-2020","captain":0,"shots":{"total":0,"on":0},"goals":{"total":0,"conceded":0,"assists":0},"passes":{"total":0,"key":0,"accuracy":0},"tackles":{"total":0,"blocks":0,"interceptions":0},"duels":{"total":0,"won":0},"dribbles":{"attempts":0,"success":0},"fouls":{"drawn":0,"committed":0},"cards":{"yellow":0,"yellowred":0,"red":0},"penalty":{"won":0,"commited":0,"success":0,"missed":0,"saved":0},"games":{"appearences":0,"minutes_played":0,"lineups":0},"substitutes":{"in":0,"out":0,"bench":2}},{"player_id":178093,"player_name":"Y. Keitel","firstname":"Yannik","lastname":"Keitel","number":null,"position":"Midfielder","age":20,"birth_date":"15/02/2000","birth_place":null,"birth_country":"Germany","nationality":"Germany","height":"185 cm","weight":null,"injured":null,"rating":"6.200000","team_id":160,"team_name":"SC Freiburg","league":"Bundesliga","season":"2019-2020","captain":0,"shots":{"total":0,"on":0},"goals":{"total":0,"conceded":0,"assists":0},"passes":{"total":8,"key":0,"accuracy":72},"tackles":{"total":0,"blocks":1,"interceptions":0},"duels":{"total":0,"won":0},"dribbles":{"attempts":0,"success":0},"fouls":{"drawn":0,"committed":2},"cards":{"yellow":0,"yellowred":0,"red":0},"penalty":{"won":0,"commited":0,"success":0,"missed":0,"saved":0},"games":{"appearences":1,"minutes_played":44,"lineups":0},"substitutes":{"in":1,"out":0,"bench":6}},{"player_id":26251,"player_name":"F. Kath","firstname":"Florian","lastname":"Kath","number":null,"position":"Midfielder","age":26,"birth_date":"21/10/1994","birth_place":"Balingen","birth_country":"Germany","nationality":"Germany","height":"185 cm","weight":"78 kg","injured":null,"rating":null,"team_id":160,"team_name":"SC Freiburg","league":"Bundesliga","season":"2019-2020","captain":0,"shots":{"total":0,"on":0},"goals":{"total":0,"conceded":0,"assists":0},"passes":{"total":0,"key":0,"accuracy":0},"tackles":{"total":0,"blocks":0,"interceptions":0},"duels":{"total":0,"won":0},"dribbles":{"attempts":0,"success":0},"fouls":{"drawn":0,"committed":0},"cards":{"yellow":0,"yellowred":0,"red":0},"penalty":{"won":0,"commited":0,"success":0,"missed":0,"saved":0},"games":{"appearences":0,"minutes_played":0,"lineups":0},"substitutes":{"in":0,"out":0,"bench":0}},{"player_id":26255,"player_name":"L. Höler","firstname":"Lucas","lastname":"Höler","number":null,"position":"Attacker","age":26,"birth_date":"10/07/1994","birth_place":"Achim","birth_country":"Germany","nationality":"Germany","height":"183 cm","weight":"80 kg","injured":null,"rating":"6.892000","team_id":160,"team_name":"SC Freiburg","league":"Bundesliga","season":"2019-2020","captain":0,"shots":{"total":35,"on":14},"goals":{"total":4,"conceded":0,"assists":2},"passes":{"total":309,"key":25,"accuracy":65},"tackles":{"total":27,"blocks":5,"interceptions":9},"duels":{"total":0,"won":0},"dribbles":{"attempts":43,"success":22},"fouls":{"drawn":57,"committed":30},"cards":{"yellow":4,"yellowred":0,"red":0},"penalty":{"won":1,"commited":1,"success":0,"missed":1,"saved":0},"games":{"appearences":25,"minutes_played":1819,"lineups":20},"substitutes":{"in":5,"out":11,"bench":5}},{"player_id":26255,"player_name":"L. Höler","firstname":"Lucas","lastname":"Höler","number":null,"position":"Attacker","age":26,"birth_date":"10/07/1994","birth_place":"Achim","birth_country":"Germany","nationality":"Germany","height":"183 cm","weight":"80 kg","injured":null,"rating":"6.500000","team_id":160,"team_name":"SC Freiburg","league":"DFB Pokal","season":"2019-2020","captain":0,"shots":{"total":1,"on":0},"goals":{"total":0,"conceded":0,"assists":0},"passes":{"total":17,"key":1,"accuracy":60},"tackles":{"total":4,"blocks":0,"interceptions":2},"duels":{"total":0,"won":0},"dribbles":{"attempts":2,"success":1},"fouls":{"drawn":1,"committed":1},"cards":{"yellow":0,"yellowred":0,"red":0},"penalty":{"won":0,"commited":0,"success":0,"missed":0,"saved":0},"games":{"appearences":2,"minutes_played":87,"lineups":0},"substitutes":{"in":2,"out":0,"bench":2}},{"player_id":26260,"player_name":"L. Waldschmidt","firstname":"Gian-Luca","lastname":"Waldschmidt","number":null,"position":"Attacker","age":24,"birth_date":"19/05/1996","birth_place":"Siegen","birth_country":"Germany","nationality":"Germany","height":"181 cm","weight":"75 kg","injured":null,"rating":"6.800000","team_id":160,"team_name":"SC Freiburg","league":"Bundesliga","season":"2019-2020","captain":0,"shots":{"total":30,"on":8},"goals":{"total":5,"conceded":0,"assists":1},"passes":{"total":194,"key":8,"accuracy":74},"tackles":{"total":7,"blocks":1,"interceptions":2},"duels":{"total":0,"won":0},"dribbles":{"attempts":25,"success":10},"fouls":{"drawn":10,"committed":8},"cards":{"yellow":1,"yellowred":0,"red":0},"penalty":{"won":1,"commited":0,"success":3,"missed":0,"saved":0},"games":{"appearences":15,"minutes_played":852,"lineups":9},"substitutes":{"in":6,"out":5,"bench":7}},{"player_id":26260,"player_name":"L. Waldschmidt","firstname":"Gian-Luca","lastname":"Waldschmidt","number":null,"position":"Attacker","age":24,"birth_date":"19/05/1996","birth_place":"Siegen","birth_country":"Germany","nationality":"Germany","height":"181 cm","weight":"75 kg","injured":null,"rating":"7.300000","team_id":160,"team_name":"SC Freiburg","league":"DFB Pokal","season":"2019-2020","captain":0,"shots":{"total":2,"on":1},"goals":{"total":1,"conceded":0,"assists":0},"passes":{"total":26,"key":1,"accuracy":86},"tackles":{"total":0,"blocks":0,"interceptions":0},"duels":{"total":0,"won":0},"dribbles":{"attempts":0,"success":0},"fouls":{"drawn":2,"committed":1},"cards":{"yellow":0,"yellowred":0,"red":0},"penalty":{"won":0,"commited":0,"success":0,"missed":0,"saved":0},"games":{"appearences":1,"minutes_played":120,"lineups":1},"substitutes":{"in":0,"out":0,"bench":0}},{"player_id":26258,"player_name":"N. Petersen","firstname":"Nils","lastname":"Petersen","number":null,"position":"Attacker","age":32,"birth_date":"06/12/1988","birth_place":"Wernigerode","birth_country":"Germany","nationality":"Germany","height":"188 cm","weight":"84 kg","injured":null,"rating":"6.952000","team_id":160,"team_name":"SC Freiburg","league":"Bundesliga","season":"2019-2020","captain":0,"shots":{"total":46,"on":15},"goals":{"total":8,"conceded":0,"assists":2},"passes":{"total":269,"key":28,"accuracy":62},"tackles":{"total":14,"blocks":4,"interceptions":8},"duels":{"total":0,"won":0},"dribbles":{"attempts":13,"success":3},"fouls":{"drawn":16,"committed":9},"cards":{"yellow":1,"yellowred":0,"red":0},"penalty":{"won":0,"commited":0,"success":1,"missed":0,"saved":0},"games":{"appearences":25,"minutes_played":1947,"lineups":20},"substitutes":{"in":5,"out":2,"bench":5}},{"player_id":26258,"player_name":"N. Petersen","firstname":"Nils","lastname":"Petersen","number":null,"position":"Attacker","age":32,"birth_date":"06/12/1988","birth_place":"Wernigerode","birth_country":"Germany","nationality":"Germany","height":"188 cm","weight":"84 kg","injured":null,"rating":"6.750000","team_id":160,"team_name":"SC Freiburg","league":"DFB Pokal","season":"2019-2020","captain":0,"shots":{"total":6,"on":0},"goals":{"total":0,"conceded":0,"assists":0},"passes":{"total":18,"key":1,"accuracy":61},"tackles":{"total":1,"blocks":0,"interceptions":0},"duels":{"total":0,"won":0},"dribbles":{"attempts":4,"success":0},"fouls":{"drawn":2,"committed":0},"cards":{"yellow":0,"yellowred":0,"red":0},"penalty":{"won":0,"commited":0,"success":0,"missed":0,"saved":0},"games":{"appearences":2,"minutes_played":177,"lineups":2},"substitutes":{"in":0,"out":1,"bench":0}},{"player_id":26253,"player_name":"B. Borello","firstname":"Brandon Joel Gaetano","lastname":"Borrello","number":null,"position":"Attacker","age":25,"birth_date":"25/07/1995","birth_place":"Adelaide","birth_country":"Australia","nationality":"Australia","height":"178 cm","weight":"79 kg","injured":null,"rating":"6.600000","team_id":160,"team_name":"SC Freiburg","league":"Bundesliga","season":"2019-2020","captain":0,"shots":{"total":7,"on":1},"goals":{"total":0,"conceded":0,"assists":0},"passes":{"total":51,"key":3,"accuracy":82},"tackles":{"total":6,"blocks":1,"interceptions":1},"duels":{"total":0,"won":0},"dribbles":{"attempts":9,"success":5},"fouls":{"drawn":9,"committed":3},"cards":{"yellow":0,"yellowred":0,"red":0},"penalty":{"won":0,"commited":0,"success":0,"missed":0,"saved":0},"games":{"appearences":7,"minutes_played":299,"lineups":4},"substitutes":{"in":3,"out":4,"bench":19}},{"player_id":26253,"player_name":"B. Borello","firstname":"Brandon Joel Gaetano","lastname":"Borrello","number":null,"position":"Attacker","age":25,"birth_date":"25/07/1995","birth_place":"Adelaide","birth_country":"Australia","nationality":"Australia","height":"178 cm","weight":"79 kg","injured":null,"rating":"7.000000","team_id":160,"team_name":"SC Freiburg","league":"DFB Pokal","season":"2019-2020","captain":0,"shots":{"total":0,"on":0},"goals":{"total":0,"conceded":0,"assists":1},"passes":{"total":34,"key":1,"accuracy":81},"tackles":{"total":2,"blocks":0,"interceptions":1},"duels":{"total":0,"won":0},"dribbles":{"attempts":4,"success":4},"fouls":{"drawn":2,"committed":3},"cards":{"yellow":1,"yellowred":0,"red":0},"penalty":{"won":0,"commited":0,"success":0,"missed":0,"saved":0},"games":{"appearences":1,"minutes_played":111,"lineups":1},"substitutes":{"in":0,"out":1,"bench":1}},{"player_id":26252,"player_name":"R. Sallai","firstname":"Roland","lastname":"Sallai","number":null,"position":"Attacker","age":23,"birth_date":"22/05/1997","birth_place":"Budapest","birth_country":"Hungary","nationality":"Hungary","height":"183 cm","weight":"77 kg","injured":null,"rating":"6.741666","team_id":160,"team_name":"SC Freiburg","league":"Bundesliga","season":"2019-2020","captain":0,"shots":{"total":17,"on":5},"goals":{"total":1,"conceded":0,"assists":0},"passes":{"total":119,"key":7,"accuracy":75},"tackles":{"total":9,"blocks":2,"interceptions":5},"duels":{"total":0,"won":0},"dribbles":{"attempts":25,"success":11},"fouls":{"drawn":24,"committed":11},"cards":{"yellow":1,"yellowred":0,"red":0},"penalty":{"won":0,"commited":0,"success":0,"missed":0,"saved":0},"games":{"appearences":12,"minutes_played":587,"lineups":6},"substitutes":{"in":6,"out":6,"bench":17}},{"player_id":26252,"player_name":"R. Sallai","firstname":"Roland","lastname":"Sallai","number":null,"position":"Attacker","age":23,"birth_date":"22/05/1997","birth_place":"Budapest","birth_country":"Hungary","nationality":"Hungary","height":"183 cm","weight":"77 kg","injured":null,"rating":"6.700000","team_id":160,"team_name":"SC Freiburg","league":"DFB Pokal","season":"2019-2020","captain":0,"shots":{"total":4,"on":1},"goals":{"total":0,"conceded":0,"assists":0},"passes":{"total":26,"key":0,"accuracy":83},"tackles":{"total":0,"blocks":0,"interceptions":0},"duels":{"total":0,"won":0},"dribbles":{"attempts":3,"success":1},"fouls":{"drawn":7,"committed":2},"cards":{"yellow":0,"yellowred":0,"red":0},"penalty":{"won":0,"commited":0,"success":0,"missed":0,"saved":0},"games":{"appearences":2,"minutes_played":123,"lineups":2},"substitutes":{"in":0,"out":2,"bench":0}},{"player_id":2913,"player_name":"Kwon Chang-Hoon","firstname":"Chang-Hoon","lastname":"Kwon","number":null,"position":"Attacker","age":26,"birth_date":"30/06/1994","birth_place":"Seoul","birth_country":"Korea Republic","nationality":"Korea Republic","height":"174 cm","weight":"66 kg","injured":null,"rating":"7.030769","team_id":160,"team_name":"SC Freiburg","league":"Bundesliga","season":"2019-2020","captain":0,"shots":{"total":12,"on":6},"goals":{"total":2,"conceded":0,"assists":0},"passes":{"total":141,"key":10,"accuracy":71},"tackles":{"total":4,"blocks":1,"interceptions":5},"duels":{"total":0,"won":0},"dribbles":{"attempts":17,"success":12},"fouls":{"drawn":15,"committed":2},"cards":{"yellow":0,"yellowred":0,"red":0},"penalty":{"won":1,"commited":0,"success":0,"missed":0,"saved":0},"games":{"appearences":15,"minutes_played":528,"lineups":6},"substitutes":{"in":9,"out":5,"bench":17}},{"player_id":2913,"player_name":"Kwon Chang-Hoon","firstname":"Chang-Hoon","lastname":"Kwon","number":null,"position":"Attacker","age":26,"birth_date":"30/06/1994","birth_place":"Seoul","birth_country":"Korea Republic","nationality":"Korea Republic","height":"174 cm","weight":"66 kg","injured":null,"rating":null,"team_id":160,"team_name":"SC Freiburg","league":"DFB Pokal","season":"2019-2020","captain":0,"shots":{"total":0,"on":0},"goals":{"total":0,"conceded":0,"assists":0},"passes":{"total":0,"key":0,"accuracy":0},"tackles":{"total":0,"blocks":0,"interceptions":0},"duels":{"total":0,"won":0},"dribbles":{"attempts":0,"success":0},"fouls":{"drawn":0,"committed":0},"cards":{"yellow":0,"yellowred":0,"red":0},"penalty":{"won":0,"commited":0,"success":0,"missed":0,"saved":0},"games":{"appearences":0,"minutes_played":0,"lineups":0},"substitutes":{"in":0,"out":0,"bench":1}},{"player_id":26247,"player_name":"J. Gondorf","firstname":"Jérôme","lastname":"Gondorf","number":null,"position":"Midfielder","age":32,"birth_date":"26/06/1988","birth_place":"Karlsruhe","birth_country":"Germany","nationality":"Germany","height":"176 cm","weight":"78 kg","injured":null,"rating":"6.850000","team_id":160,"team_name":"SC Freiburg","league":"Bundesliga","season":"2019-2020","captain":0,"shots":{"total":2,"on":1},"goals":{"total":0,"conceded":0,"assists":0},"passes":{"total":29,"key":1,"accuracy":72},"tackles":{"total":7,"blocks":2,"interceptions":1},"duels":{"total":0,"won":0},"dribbles":{"attempts":1,"success":0},"fouls":{"drawn":2,"committed":4},"cards":{"yellow":1,"yellowred":0,"red":0},"penalty":{"won":0,"commited":0,"success":0,"missed":0,"saved":0},"games":{"appearences":2,"minutes_played":122,"lineups":2},"substitutes":{"in":0,"out":2,"bench":7}},{"player_id":26247,"player_name":"J. Gondorf","firstname":"Jérôme","lastname":"Gondorf","number":null,"position":"Midfielder","age":32,"birth_date":"26/06/1988","birth_place":"Karlsruhe","birth_country":"Germany","nationality":"Germany","height":"176 cm","weight":"78 kg","injured":null,"rating":"6.700000","team_id":160,"team_name":"SC Freiburg","league":"DFB Pokal","season":"2019-2020","captain":0,"shots":{"total":0,"on":0},"goals":{"total":0,"conceded":0,"assists":0},"passes":{"total":16,"key":0,"accuracy":72},"tackles":{"total":0,"blocks":0,"interceptions":0},"duels":{"total":0,"won":0},"dribbles":{"attempts":2,"success":2},"fouls":{"drawn":3,"committed":2},"cards":{"yellow":1,"yellowred":0,"red":0},"penalty":{"won":0,"commited":0,"success":0,"missed":0,"saved":0},"games":{"appearences":1,"minutes_played":42,"lineups":0},"substitutes":{"in":1,"out":0,"bench":2}},{"player_id":26259,"player_name":"M. Terrazzino","firstname":"Marco","lastname":"Terrazzino","number":null,"position":"Attacker","age":29,"birth_date":"15/04/1991","birth_place":"Mannheim","birth_country":"Germany","nationality":"Germany","height":"177 cm","weight":"77 kg","injured":null,"rating":null,"team_id":160,"team_name":"SC Freiburg","league":"Bundesliga","season":"2019-2020","captain":0,"shots":{"total":0,"on":0},"goals":{"total":0,"conceded":0,"assists":0},"passes":{"total":0,"key":0,"accuracy":0},"tackles":{"total":0,"blocks":0,"interceptions":0},"duels":{"total":0,"won":0},"dribbles":{"attempts":0,"success":0},"fouls":{"drawn":0,"committed":0},"cards":{"yellow":0,"yellowred":0,"red":0},"penalty":{"won":0,"commited":0,"success":0,"missed":0,"saved":0},"games":{"appearences":0,"minutes_played":0,"lineups":0},"substitutes":{"in":0,"out":0,"bench":0}},{"player_id":26259,"player_name":"M. Terrazzino","firstname":"Marco","lastname":"Terrazzino","number":null,"position":"Attacker","age":29,"birth_date":"15/04/1991","birth_place":"Mannheim","birth_country":"Germany","nationality":"Germany","height":"177 cm","weight":"77 kg","injured":null,"rating":null,"team_id":160,"team_name":"SC Freiburg","league":"DFB Pokal","season":"2019-2020","captain":0,"shots":{"total":0,"on":0},"goals":{"total":0,"conceded":0,"assists":0},"passes":{"total":0,"key":0,"accuracy":0},"tackles":{"total":0,"blocks":0,"interceptions":0},"duels":{"total":0,"won":0},"dribbles":{"attempts":0,"success":0},"fouls":{"drawn":0,"committed":0},"cards":{"yellow":0,"yellowred":0,"red":0},"penalty":{"won":0,"commited":0,"success":0,"missed":0,"saved":0},"games":{"appearences":0,"minutes_played":0,"lineups":0},"substitutes":{"in":0,"out":0,"bench":0}},{"player_id":26256,"player_name":"T. Kleindienst","firstname":"Tim","lastname":"Kleindienst","number":null,"position":"Attacker","age":25,"birth_date":"31/08/1995","birth_place":"Luckenwalde","birth_country":"Germany","nationality":"Germany","height":"194 cm","weight":"84 kg","injured":null,"rating":null,"team_id":160,"team_name":"SC Freiburg","league":"Bundesliga","season":"2019-2020","captain":0,"shots":{"total":0,"on":0},"goals":{"total":0,"conceded":0,"assists":0},"passes":{"total":0,"key":0,"accuracy":0},"tackles":{"total":0,"blocks":0,"interceptions":0},"duels":{"total":0,"won":0},"dribbles":{"attempts":0,"success":0},"fouls":{"drawn":0,"committed":0},"cards":{"yellow":0,"yellowred":0,"red":0},"penalty":{"won":0,"commited":0,"success":0,"missed":0,"saved":0},"games":{"appearences":0,"minutes_played":0,"lineups":0},"substitutes":{"in":0,"out":0,"bench":1}}]